g36_ahu_faults/faults/__init__.py
g36_ahu_faults/tests/__init__.py
g36_ahu_faults/tests/unit/__init__.py
g36_ahu_faults/tests/unit/test_ahu_fc1.py
g36_ahu_faults/tests/unit/test_ahu_fc10.py
g36_ahu_faults/tests/unit/test_ahu_fc11.py
g36_ahu_faults/tests/unit/test_ahu_fc12.py
g36_ahu_faults/tests/unit/test_ahu_fc13.py
g36_ahu_faults/tests/unit/test_ahu_fc14.py
g36_ahu_faults/tests/unit/test_ahu_fc15.py
g36_ahu_faults/tests/unit/test_ahu_fc2.py
g36_ahu_faults/tests/unit/test_ahu_fc3.py
g36_ahu_faults/tests/unit/test_ahu_fc4.py
g36_ahu_faults/tests/unit/test_ahu_fc5.py
g36_ahu_faults/tests/unit/test_ahu_fc6.py
g36_ahu_faults/tests/unit/test_ahu_fc7.py
g36_ahu_faults/tests/unit/test_ahu_fc8.py
g36_ahu_faults/tests/unit/test_ahu_fc9.py
g36_ahu_faults-0.0.1.dist-info/LICENSE
g36_ahu_faults-0.0.1.dist-info/METADATA
g36_ahu_faults-0.0.1.dist-info/WHEEL
g36_ahu_faults-0.0.1.dist-info/top_level.txt
g36_ahu_faults-0.0.1.dist-info/RECORD
