Metadata-Version: 2.1
Name: g36-ahu-faults
Version: 0.0.1
Summary: Package for fault detection and diagnosis of AHUs using G36 fault conditions
Author-email: Ben Bartling <ben.bartling@gmail.com>, Andrew Rodgers <andrew@aceiotsolutions.com>
Project-URL: Homepage, https://github.com/ACE-IoT-Solutions/g36-ahu-faults
Classifier: Programming Language :: Python :: 3
Classifier: License :: OSI Approved :: MIT License
Classifier: Operating System :: OS Independent
Requires-Python: >=3.7
License-File: LICENSE
